Metadata-Version: 2.1
Name: thenewboston-python-client
Version: 0.0.2
Summary: UNKNOWN
Home-page: UNKNOWN
License: UNKNOWN
Platform: UNKNOWN
